Workbook

Sheet Sales_Data
A1: Order_ID | B1: Region | C1: Salesperson | D1: Left | E1: Product | F1: Quantity | G1: High/Low | H1: Unit_Price | I1: Round | J1: Total_Sales | K1: Sales_Date | L1: Month | M1: GST | N1: Amout_payable | O1: Grand Total | P1: Product Category
A2: 301 | B2: North | C2: Amit | D2: =LEFT(C2,2) -> Am | E2: Laptop | F2: 2 | G2: =IF(F2>=3,"High","Low") -> Low | H2: 45000 | I2: =ROUND(H2,10000) -> 45000 | J2: =PRODUCT(F2,H2) -> 90000 | K2: 05-01-2025 | L2: =TEXT(K2, "MMMM") -> January | M2: =VLOOKUP(E2,Product_Master!A1:C4,3,0) -> 0.18 | N2: =SUM(J2*0.18) -> 16200 | O2: =SUM(J2,N2) -> 106200
A3: 306 | B3: South | C3: Riya | D3: =LEFT(C3,2) -> Ri | E3: Laptop | F3: 2 | G3: =IF(F3>=3,"High","Low") -> Low | H3: 45000 | I3: =ROUND(H3,10000) -> 45000 | J3: =PRODUCT(F3,H3) -> 90000 | K3: 18-01-2025 | L3: =TEXT(K3, "MMMM") -> January | M3: =VLOOKUP(E3,Product_Master!A1:C4,3,0) -> 0.18 | N3: =SUM(J3*0.18) -> 16200 | O3: =SUM(J3,N3) -> 106200
A4: 302 | B4: South | C4: Riya | D4: =LEFT(C4,2) -> Ri | E4: Mobile | F4: 5 | G4: =IF(F4>=3,"High","Low") -> High | H4: 15000 | I4: =ROUND(H4,10000) -> 15000 | J4: =PRODUCT(F4,H4) -> 75000 | K4: 07-01-2025 | L4: =TEXT(K4, "MMMM") -> January | M4: =VLOOKUP(E4,Product_Master!A2:C5,3,0) -> 0.12 | N4: =SUM(J4*0.18) -> 13500 | O4: =SUM(J4,N4) -> 88500
A5: 305 | B5: North | C5: Amit | D5: =LEFT(C5,2) -> Am | E5: Mobile | F5: 4 | G5: =IF(F5>=3,"High","Low") -> High | H5: 15000 | I5: =ROUND(H5,10000) -> 15000 | J5: =PRODUCT(F5,H5) -> 60000 | K5: 15-01-2025 | L5: =TEXT(K5, "MMMM") -> January | M5: =VLOOKUP(E5,Product_Master!A2:C5,3,0) -> 0.12 | N5: =SUM(J5*0.18) -> 10800 | O5: =SUM(J5,N5) -> 70800 | R5: Max | S5: =MAX(O2:O7) -> 106200
A6: 303 | B6: East | C6: Kunal | D6: =LEFT(C6,2) -> Ku | E6: Tablet | F6: 3 | G6: =IF(F6>=3,"High","Low") -> High | H6: 18000 | I6: =ROUND(H6,10000) -> 18000 | J6: =PRODUCT(F6,H6) -> 54000 | K6: 10-01-2025 | L6: =TEXT(K6, "MMMM") -> January | M6: =VLOOKUP(E6,Product_Master!A3:C6,3,0) -> 0.12 | N6: =SUM(J6*0.18) -> 9720 | O6: =SUM(J6,N6) -> 63720 | R6: Min | S6: =MIN(O2:O7) -> 53100
A7: 304 | B7: West | C7: Neha | D7: =LEFT(C7,2) -> Ne | E7: Laptop | F7: 1 | G7: =IF(F7>=3,"High","Low") -> Low | H7: 45000 | I7: =ROUND(H7,10000) -> 45000 | J7: =PRODUCT(F7,H7) -> 45000 | K7: 12-01-2025 | L7: =TEXT(K7, "MMMM") -> January | M7: =VLOOKUP(E7,Product_Master!A1:C4,3,0) -> 0.18 | N7: =SUM(J7*0.18) -> 8100 | O7: =SUM(J7,N7) -> 53100
R8: Total No. of Order | T8: =COUNTA(A2:A7) -> 6
B10: Region | C10: Total Sales
B11: North | C11: =SUMIF(B2:B7,"North",O2:O7) -> 177000
B12: South | C12: =SUMIF(B2:B7,"South",O2:O7) -> 194700
B13: East | C13: =SUMIF(B2:B7,"East",O2:O7) -> 63720
B14: West | C14: =SUMIF(B2:B7,"West",O2:O7) -> 53100

Sheet Product_Master
A1: Product | B1: Category | C1: GST_%
A2: Laptop | B2: Electronics | C2: 0.18
A3: Mobile | B3: Electronics | C3: 0.12
A4: Tablet | B4: Electronics | C4: 0.12

Sheet Student_Marks
A1: Student_ID | B1: Name | D1: Maths | E1: Statistics | F1: Excel | G1: Attendance_% | H1: Average Marks | I1: Eligiblility
A2: 1 | B2: Rahul | C2: =_xlfn.CONCAT(A2,B2) -> 1Rahul | D2: 78 | E2: 82 | F2: 85 | G2: 92 | H2: =AVERAGE(D2,E2,F2) -> 81.666667 | I2: =IF(G2>=80,"Eligible","Not Eligible") -> Eligible
A3: 2 | B3: Sneha | C3: =_xlfn.CONCAT(A3,B3) -> 2Sneha | D3: 88 | E3: 91 | F3: 90 | G3: 96 | H3: =AVERAGE(D3,E3,F3) -> 89.666667 | I3: =IF(G3>=80,"Eligible","Not Eligible") -> Eligible
A4: 3 | B4: Arjun | C4: =_xlfn.CONCAT(A4,B4) -> 3Arjun | D4: 65 | E4: 70 | F4: 72 | G4: 85 | H4: =AVERAGE(D4,E4,F4) -> 69 | I4: =IF(G4>=80,"Eligible","Not Eligible") -> Eligible | M4: Median for Statistics | O4: =MEDIAN(E2:E6) -> 82
A5: 4 | B5: Pooja | C5: =_xlfn.CONCAT(A5,B5) -> 4Pooja | D5: 92 | E5: 89 | F5: 94 | G5: 98 | H5: =AVERAGE(D5,E5,F5) -> 91.666667 | I5: =IF(G5>=80,"Eligible","Not Eligible") -> Eligible
A6: 5 | B6: Vikas | C6: =_xlfn.CONCAT(A6,B6) -> 5Vikas | D6: 55 | E6: 60 | F6: 58 | G6: 80 | H6: =AVERAGE(D6,E6,F6) -> 57.666667 | I6: =IF(G6>=80,"Eligible","Not Eligible") -> Eligible
